[
	{
		"id": 1,
		"team": "Краснодар",
		"game": 18,
		"win": 11,
		"draw": 6,
		"lose": 1,
		"difference": "34-12",
		"points": 39
	},
	{
		"id": 2,
		"team": "Зенит",
		"game": 18,
		"win": 12,
		"draw": 3,
		"lose": 3,
		"difference": "37-12",
		"points": 39
	},

	{
		"id": 3,
		"team": "Спартак",
		"game": 18,
		"win": 11,
		"draw": 4,
		"lose": 3,
		"difference": "36-14",
		"points": 37
	},
	{
		"id": 4,
		"team": "Динамо",
		"game": 18,
		"win": 10,
		"draw": 5,
		"lose": 3,
		"difference": "37-20",
		"points": 35
	},
	{
		"id": 5,
		"team": "Локомотив",
		"game": 18,
		"win": 11,
		"draw": 2,
		"lose": 5,
		"difference": "33-26",
		"points": 35
	},
	{
		"id": 6,
		"team": "ЦСКА",
		"game": 18,
		"win": 9,
		"draw": 4,
		"lose": 5,
		"difference": "28-14",
		"points": 31
	},
	{
		"id": 7,
		"team": "Ростов",
		"game": 18,
		"win": 7,
		"draw": 5,
		"lose": 6,
		"difference": "29-28",
		"points": 26
	},
	{
		"id": 8,
		"team": "Рубин",
		"game": 18,
		"win": 7,
		"draw": 5,
		"lose": 6,
		"difference": "25-26",
		"points": 26
	},
	{
		"id": 9,
		"team": "Акрон",
		"game": 18,
		"win": 6,
		"draw": 4,
		"lose": 8,
		"difference": "22-34",
		"points": 22
	},
	{
		"id": 10,
		"team": "Крылья Советов",
		"game": 18,
		"win": 5,
		"draw": 3,
		"lose": 10,
		"difference": "19-29",
		"points": 18
	},
	{
		"id": 11,
		"team": "Динамо Мх",
		"game": 18,
		"win": 3,
		"draw": 8,
		"lose": 7,
		"difference": "11-17",
		"points": 17
	},
	{
		"id": 12,
		"team": "Парин НН",
		"game": 18,
		"win": 4,
		"draw": 4,
		"lose": 10,
		"difference": "15-34",
		"points": 16
	},
	{
		"id": 13,
		"team": "Химки",
		"game": 18,
		"win": 3,
		"draw": 7,
		"lose": 8,
		"difference": "22-35",
		"points": 16
	},
	{
		"id": 14,
		"team": "Факел",
		"game": 18,
		"win": 2,
		"draw": 8,
		"lose": 8,
		"difference": "11-25",
		"points": 14
	},
	{
		"id": 15,
		"team": "Ахмат",
		"game": 18,
		"win": 2,
		"draw": 7,
		"lose": 9,
		"difference": "16-32",
		"points": 13
	},
	{
		"id": 16,
		"team": "Оренбург",
		"game": 18,
		"win": 1,
		"draw": 5,
		"lose": 12,
		"difference": "16-33",
		"points": 8
	}
]
